ztree2python/__init__.py
ztree2python/ztree2python.py
ztree2python-0.99.2.dist-info/LICENSE
ztree2python-0.99.2.dist-info/METADATA
ztree2python-0.99.2.dist-info/WHEEL
ztree2python-0.99.2.dist-info/top_level.txt
ztree2python-0.99.2.dist-info/RECORD
