Metadata-Version: 2.1
Name: ztree2python
Version: 0.99.2
Summary: Read z-Tree data files.
Home-page: https://github.com/takekan/ztree2python
Author: Kan Takeuchi
Author-email: takeuchi.kan@gmail.com
Keywords: z-Tree,z-tree,zTree,ztree,ztree2python,ztree2stata,economic experiment,experimental economics
Classifier: Intended Audience :: Science/Research
License-File: LICENSE
Requires-Dist: pandas
